LICENSE
README.md
setup.py
hyper_io3.egg-info/PKG-INFO
hyper_io3.egg-info/SOURCES.txt
hyper_io3.egg-info/dependency_links.txt
hyper_io3.egg-info/requires.txt
hyper_io3.egg-info/top_level.txt
hyperio/__init__.py
hyperio/hyperio.py